l_command/__init__.py
l_command/cli.py
l_command/constants.py
l_command/utils.py
l_command/handlers/__init__.py
l_command/handlers/archive.py
l_command/handlers/base.py
l_command/handlers/binary.py
l_command/handlers/csv.py
l_command/handlers/default.py
l_command/handlers/directory.py
l_command/handlers/image.py
l_command/handlers/json.py
l_command/handlers/markdown.py
l_command/handlers/media.py
l_command/handlers/pdf.py
l_command/handlers/xml.py
l_command/handlers/yaml.py
l_command-0.3.0.dist-info/METADATA
l_command-0.3.0.dist-info/WHEEL
l_command-0.3.0.dist-info/entry_points.txt
l_command-0.3.0.dist-info/licenses/LICENSE
l_command-0.3.0.dist-info/RECORD
