Metadata-Version: 2.4
Name: l-command
Version: 0.3.0
Summary: Smart file and directory viewer
Project-URL: Homepage, https://github.com/gyu-don/l-command
Project-URL: Repository, https://github.com/gyu-don/l-command
Author-email: gyu-don <takumi.kt@gmail.com>
License: Apache-2.0
License-File: LICENSE
Keywords: cli,directory-viewer,file-viewer,ls
Classifier: Development Status :: 3 - Alpha
Classifier: Environment :: Console
Classifier: Intended Audience :: Developers
Classifier: License :: OSI Approved :: Apache Software License
Classifier: Operating System :: OS Independent
Classifier: Programming Language :: Python :: 3
Classifier: Topic :: System :: Filesystems
Classifier: Topic :: Utilities
Requires-Python: >=3.11
